py_io_capture/__init__.py
py_io_capture/common.py
py_io_capture/driver.py
py_io_capture/io_capture.py
py_io_capture/report.py
py_io_capture/report_table.py
python_io_capture-0.0.1.3.dist-info/METADATA
python_io_capture-0.0.1.3.dist-info/WHEEL
python_io_capture-0.0.1.3.dist-info/top_level.txt
python_io_capture-0.0.1.3.dist-info/RECORD
